pyastar/__init__.py
pyastar/astar.py
pyastar/interface.py
pyastar/problem.py
pyastar/version.py
pyastar/examples/__init__.py
pyastar/examples/example_graph.py
pyastar/examples/example_grid.py
pyastar/usage/__init__.py
pyastar/usage/usage_graph.py
pyastar/usage/usage_grid.py
pyastar/util/__init__.py
pyastar/util/factory.py
pyastar/util/graph.py
pyastar/util/grid.py
pyastar/util/heuristics.py
pyastar/util/node.py
pyastar/util/pq.py
pyastar-0.1.dist-info/LICENSE
pyastar-0.1.dist-info/METADATA
pyastar-0.1.dist-info/WHEEL
pyastar-0.1.dist-info/top_level.txt
pyastar-0.1.dist-info/RECORD
