Metadata-Version: 2.1
Name: pyastar
Version: 0.1
Summary: AStar Algorithm
Home-page: https://www.egr.msu.edu/coinlab/pyastar/
Author: Julian Blank
Author-email: blankjul@egr.msu.edu
License: Apache License 2.0
Keywords: graph,heuristic search
Platform: any
Classifier: Intended Audience :: Developers
Classifier: Intended Audience :: Science/Research
Classifier: Operating System :: OS Independent
Classifier: License :: OSI Approved :: Apache Software License
Classifier: Programming Language :: Python
Classifier: Programming Language :: Python :: 3
Classifier: Programming Language :: Python :: 3.6
Classifier: Programming Language :: Python :: 3.7
Classifier: Topic :: Scientific/Engineering
Classifier: Topic :: Scientific/Engineering :: Artificial Intelligence
Classifier: Topic :: Scientific/Engineering :: Mathematics
Requires-Python: >=3.6
